{
    "url_producto": "https://www.drogueriascolsubsidio.com/anillo-duo-g-vibration-4005800012921/p",
    "fecha_hora_scraping": "2021-06-14 05:29:47",
    "breadcumb": "colsubsidio|medicamentos|salud sexual|lubricantes y dispositivos",
    "titulo": "ANILLO DUO G VIBRATION",
    "nombre_imagen": "./web_scraping/data/img/ANILLO_DUO_G_VIBRATION.jpg",
    "presentacion": "UNIDAD",
    "precio": {
        "bestPrice": "$22.950",
        "precioPorSku js-PUM": "Unidad a $22.950,00"
    },
    "descripcion": "anillo duo g vibration",
    "atributos": [
        [
            "Presentaci\u00f3n",
            "UNIDAD"
        ],
        [
            "Concentracion",
            "N/A N/A"
        ],
        [
            "Principio activo",
            ""
        ],
        [
            "Laboratorio",
            "BEIERSDORF SA"
        ],
        [
            "Registro Invima",
            "2005V-0003568"
        ],
        [
            "Color",
            ""
        ]
    ]
}