{
    "url_producto": "https://www.drogueriascolsubsidio.com/demtris-unguento-8436024611908/p",
    "fecha_hora_scraping": "2021-06-14 00:10:59",
    "breadcumb": "colsubsidio|medicamentos|formulados",
    "titulo": "DEMTRIS UNGUENTO",
    "nombre_imagen": "./web_scraping/data/img/DEMTRIS_UNGUENTO.jpg",
    "presentacion": "TUBO X 30 G",
    "precio": {
        "bestPrice": "$26.400",
        "precioPorSku js-PUM": "Gramo a $880,00"
    },
    "descripcion": "este producto es un medicamento. no exceder su consumo. leer indicaciones y contraindicaciones. si los s\u00edntomas persisten, consultar al m\u00e9dico. venta bajo f\u00f3rmula m\u00e9dica.",
    "atributos": [
        [
            "Presentaci\u00f3n",
            "TUBO X 30 G"
        ],
        [
            "Concentracion",
            "250 MG 100 MG 10 UI"
        ],
        [
            "Principio activo",
            "NEOMICINA SULFATO NISTATINA TRIAMCINOLONA ACETONIDO"
        ],
        [
            "Laboratorio",
            "BCN MEDICAL SA"
        ],
        [
            "Registro Invima",
            "2017M-0017743"
        ],
        [
            "Color",
            ""
        ]
    ]
}