{
    "url_producto": "https://www.drogueriascolsubsidio.com/genfargrip-tableta-7702605107995/p",
    "fecha_hora_scraping": "2021-06-13 16:39:43",
    "titulo": "GENFARGRIP TABLETA",
    "nombre_imagen": "./web_scraping/data/img/GENFARGRIP_TABLETA.jpg",
    "presentacion": "SOBRE X 4 TAB",
    "precio": {
        "bestPrice": "$4.850",
        "precioPorSku js-PUM": "Unidad a $194,00"
    },
    "descripcion": "este producto es un medicamento. no exceder su consumo. leer indicaciones y contraindicaciones. si los sintomas persisten, consultar al m\u00e9dico.",
    "atributos": [
        [
            "Presentaci\u00f3n",
            "SOBRE X 4 TAB"
        ],
        [
            "Concentracion",
            "500 MG 10 MG 5 MG"
        ],
        [
            "Principio activo",
            "ACETAMINOFEN FENILEFRINA CLORHIDRATO CETIRIZINA DICLORHIDRATO"
        ],
        [
            "Laboratorio",
            "GENFAR SA"
        ],
        [
            "Registro Invima",
            "2013M-0001930-R1"
        ],
        [
            "Color",
            ""
        ]
    ]
}