{
    "url_producto": "https://www.drogueriascolsubsidio.com/jeringa-10ml-con-aguja-21g-x-1-12-pulgadas-7707228361793/p",
    "fecha_hora_scraping": "2021-06-14 02:05:00",
    "breadcumb": "colsubsidio|equipos de cuidado en casa|accesorios m\u00e9dicos",
    "titulo": "JERINGA 10ML CON AGUJA 21G X 1 1/2 PULGADAS",
    "nombre_imagen": "./web_scraping/data/img/JERINGA_10ML_CON_AGUJA_21G_X_1_12_PULGADAS.jpg",
    "presentacion": "UNIDAD",
    "precio": {
        "bestPrice": "$290",
        "precioPorSku js-PUM": "Unidad a $290,00"
    },
    "descripcion": "jeringa 10ml con aguja 21g x 1 1/2 pulga",
    "atributos": [
        [
            "Presentaci\u00f3n",
            "UNIDAD"
        ],
        [
            "Concentracion",
            "N/A N/A"
        ],
        [
            "Principio activo",
            "INSUMOS PARA LA SALUD"
        ],
        [
            "Laboratorio",
            "ALFA TRADING SAS"
        ],
        [
            "Registro Invima",
            "2018DM-0001797-R1"
        ],
        [
            "Color",
            ""
        ]
    ]
}