{
    "url_producto": "https://www.drogueriascolsubsidio.com/loratadina-10-mg-tableta-la-sante-7703763320127/p",
    "fecha_hora_scraping": "2021-06-13 23:11:50",
    "breadcumb": "colsubsidio|medicamentos|formulados",
    "titulo": "LORATADINA 10 MG TABLETA LA SANTE",
    "nombre_imagen": "./web_scraping/data/img/LORATADINA_10_MG_TABLETA_LA_SANTE.jpg",
    "presentacion": "CAJA X 10 TAB",
    "precio": {
        "bestPrice": "$3.350",
        "precioPorSku js-PUM": "Tableta a $335,00"
    },
    "descripcion": "este producto es un medicamento. no exceder su consumo. leer indicaciones y contraindicaciones. si los s\u00edntomas persisten, consultar al m\u00e9dico. venta bajo f\u00f3rmula m\u00e9dica.",
    "atributos": [
        [
            "Presentaci\u00f3n",
            "CAJA X 10 TAB"
        ],
        [
            "Concentracion",
            "10 MG"
        ],
        [
            "Principio activo",
            "LORATADINA"
        ],
        [
            "Laboratorio",
            "LABORATORIOS LA SANTE SA"
        ],
        [
            "Registro Invima",
            "2016M-004166-R2"
        ],
        [
            "Color",
            ""
        ]
    ]
}