{
    "url_producto": "https://www.drogueriascolsubsidio.com/oferta-oscillococcinum-x-2und-precio-especial-7702207700365/p",
    "fecha_hora_scraping": "2021-06-14 08:53:43",
    "breadcumb": "colsubsidio|medicamentos|medicina alternativa|homeopaticos",
    "titulo": "OFERTA OSCILLOCOCCINUM X 2UND PRECIO ESPECIAL",
    "nombre_imagen": "./web_scraping/data/img/OFERTA_OSCILLOCOCCINUM_X_2UND_PRECIO_ESPECIAL.jpg",
    "presentacion": "2 CAJASX6TUB",
    "precio": {
        "bestPrice": "$49.100",
        "precioPorSku js-PUM": "Unidad a $4.091,67"
    },
    "descripcion": "of-oscillococcinum 2cjx6tub dosis p:e lf",
    "atributos": [
        [
            "Presentaci\u00f3n",
            "2 CAJASX6TUB"
        ],
        [
            "Concentracion",
            "N/A N/A"
        ],
        [
            "Principio activo",
            "MULTIPLES COMPONENTES"
        ],
        [
            "Laboratorio",
            "LABORATORIO FRANCO COLOMBIANO SAS"
        ],
        [
            "Registro Invima",
            "MH2019-0000697-R1"
        ],
        [
            "Color",
            ""
        ]
    ]
}